LICENSE.txt
MANIFEST.in
README.rst
setup.py
cmsplugin_randomquote/__init__.py
cmsplugin_randomquote/admin.py
cmsplugin_randomquote/cms_plugins.py
cmsplugin_randomquote/models.py
cmsplugin_randomquote.egg-info/PKG-INFO
cmsplugin_randomquote.egg-info/SOURCES.txt
cmsplugin_randomquote.egg-info/dependency_links.txt
cmsplugin_randomquote.egg-info/not-zip-safe
cmsplugin_randomquote.egg-info/requires.txt
cmsplugin_randomquote.egg-info/top_level.txt
cmsplugin_randomquote/migrations/0001_initial.py
cmsplugin_randomquote/migrations/0002_author_url_field.py
cmsplugin_randomquote/migrations/__init__.py
cmsplugin_randomquote/templates/cmsplugin_randomquote/quote.html