Metadata-Version: 1.0
Name: cmsplugin-randomquote
Version: 0.1.3
Summary: Random quote plugin for the django CMS.
Home-page: http://github.com/gwrtheyrn/cmsplugin-randomquote
Author: Danilo Bargen
Author-email: gezuru@gmail.com
License: MIT
Keywords: django django-cms cms plugin quotes testimonials
Platform: UNKNOWN
